pcy/__init__.py
pcy/rule_based/__init__.py
pcy/rule_based/dictionary/__init__.py
pcy/rule_based/dictionary/_node.py
pcy/rule_based/dictionary/autocomplete.py
pcy/rule_based/dictionary/dictionary_generator.py
pcy-0.2.0.dist-info/LICENSE
pcy-0.2.0.dist-info/METADATA
pcy-0.2.0.dist-info/WHEEL
pcy-0.2.0.dist-info/top_level.txt
pcy-0.2.0.dist-info/RECORD
